yacryptopan.py
yacryptopan-1.0.2.dist-info/licenses/LICENSE
yacryptopan-1.0.2.dist-info/METADATA
yacryptopan-1.0.2.dist-info/WHEEL
yacryptopan-1.0.2.dist-info/top_level.txt
yacryptopan-1.0.2.dist-info/RECORD
